README.md
pyproject.toml
setup.py
mobio/sdks/__init__.py
mobio/sdks/dedupe/__init__.py
mobio/sdks/dedupe/_init.py
mobio/sdks/dedupe/_typing.py
mobio/sdks/dedupe/api.py
mobio/sdks/dedupe/backport.py
mobio/sdks/dedupe/blocking.py
mobio/sdks/dedupe/canonical.py
mobio/sdks/dedupe/canopy_index.py
mobio/sdks/dedupe/clustering.py
mobio/sdks/dedupe/convenience.py
mobio/sdks/dedupe/core.py
mobio/sdks/dedupe/cpredicates.c
mobio/sdks/dedupe/cpredicates.cpython-311-x86_64-linux-gnu.so
mobio/sdks/dedupe/cpredicates.pyx
mobio/sdks/dedupe/datamodel.py
mobio/sdks/dedupe/index.py
mobio/sdks/dedupe/labeler.py
mobio/sdks/dedupe/levenshtein.py
mobio/sdks/dedupe/predicate_functions.py
mobio/sdks/dedupe/predicates.py
mobio/sdks/dedupe/py.typed
mobio/sdks/dedupe/serializer.py
mobio/sdks/dedupe/tfidf.py
mobio/sdks/dedupe/training.py
mobio/sdks/dedupe/variables/__init__.py
mobio/sdks/dedupe/variables/base.py
mobio/sdks/dedupe/variables/categorical_type.py
mobio/sdks/dedupe/variables/exact.py
mobio/sdks/dedupe/variables/exists.py
mobio/sdks/dedupe/variables/interaction.py
mobio/sdks/dedupe/variables/latlong.py
mobio/sdks/dedupe/variables/price.py
mobio/sdks/dedupe/variables/set.py
mobio/sdks/dedupe/variables/string.py
mobio_dedupe_sdk_test.egg-info/PKG-INFO
mobio_dedupe_sdk_test.egg-info/SOURCES.txt
mobio_dedupe_sdk_test.egg-info/dependency_links.txt
mobio_dedupe_sdk_test.egg-info/namespace_packages.txt
mobio_dedupe_sdk_test.egg-info/requires.txt
mobio_dedupe_sdk_test.egg-info/top_level.txt